locute/__init__.py
locute/inset.py
locute/lib.py
locute/utils_p/__init__.py
locute/utils_p/memory_normalizer/__init__.py
locute/utils_p/memory_normalizer/headers.py
locute-1.0.0b5.dist-info/METADATA
locute-1.0.0b5.dist-info/WHEEL
locute-1.0.0b5.dist-info/RECORD
