Metadata-Version: 2.1
Name: locute
Version: 1.0.0b5
Summary: Simple localisation library
Author: Y
Requires-Python: >=3.11,<4.0
Classifier: Programming Language :: Python :: 3
Classifier: Programming Language :: Python :: 3.11
Requires-Dist: fluent-runtime (>=0.4.0,<0.5.0)
Requires-Dist: requests (>=2.31.0,<3.0.0)
